ordinalcorr/__init__.py
ordinalcorr/corrmatrix.py
ordinalcorr/dichotomous.py
ordinalcorr/polytomous.py
ordinalcorr/types.py
ordinalcorr/validation.py
ordinalcorr-0.7.0.dist-info/METADATA
ordinalcorr-0.7.0.dist-info/WHEEL
ordinalcorr-0.7.0.dist-info/licenses/LICENSE
ordinalcorr-0.7.0.dist-info/RECORD
