Metadata-Version: 2.4
Name: ordinalcorr
Version: 0.7.0
Summary: correlation coefficients for ordinal-scaled variables
Project-URL: Homepage, https://github.com/nigimitama/ordinalcorr
Project-URL: Repository, https://github.com/nigimitama/ordinalcorr.git
Author-email: Masayoshi Mita <nigimitama16@gmail.com>
License-Expression: MIT
License-File: LICENSE
Keywords: correlation,discrete,ordinal,statistics
Classifier: License :: OSI Approved :: MIT License
Classifier: Operating System :: OS Independent
Classifier: Programming Language :: Python :: 3.10
Classifier: Programming Language :: Python :: 3.11
Classifier: Programming Language :: Python :: 3.12
Requires-Python: >=3.10
Requires-Dist: numpy>=1.23.0
Requires-Dist: pandas>=1.0.0
Requires-Dist: scipy>=1.8.0
